<annotation>
	<folder>JPEGImages</folder>
	<filename>fire2818.png</filename>
	<path>C:\lees_project\mEPaper_project\VOCdevkit\mVOC2019\JPEGImages\fire2818.png</path>
	<source>
		<database>Unknown</database>
	</source>
	<size>
		<width>224</width>
		<height>224</height>
		<depth>3</depth>
	</size>
	<segmented>0</segmented>
	<object>
		<name>fire_h</name>
		<pose>Unspecified</pose>
		<truncated>0</truncated>
		<difficult>0</difficult>
		<bndbox>
			<xmin>119</xmin>
			<ymin>114</ymin>
			<xmax>133</xmax>
			<ymax>143</ymax>
		</bndbox>
	</object>
	<object>
		<name>fire_h</name>
		<pose>Unspecified</pose>
		<truncated>0</truncated>
		<difficult>0</difficult>
		<bndbox>
			<xmin>84</xmin>
			<ymin>113</ymin>
			<xmax>112</xmax>
			<ymax>131</ymax>
		</bndbox>
	</object>
	<object>
		<name>fire_l</name>
		<pose>Unspecified</pose>
		<truncated>0</truncated>
		<difficult>0</difficult>
		<bndbox>
			<xmin>81</xmin>
			<ymin>124</ymin>
			<xmax>92</xmax>
			<ymax>140</ymax>
		</bndbox>
	</object>
	<object>
		<name>fire_l</name>
		<pose>Unspecified</pose>
		<truncated>0</truncated>
		<difficult>0</difficult>
		<bndbox>
			<xmin>57</xmin>
			<ymin>120</ymin>
			<xmax>71</xmax>
			<ymax>139</ymax>
		</bndbox>
	</object>
	<object>
		<name>fire_l</name>
		<pose>Unspecified</pose>
		<truncated>0</truncated>
		<difficult>0</difficult>
		<bndbox>
			<xmin>74</xmin>
			<ymin>130</ymin>
			<xmax>79</xmax>
			<ymax>137</ymax>
		</bndbox>
	</object>
</annotation>
