<annotation>
	<folder>fire</folder>
	<filename>Firefighterhelmetcaminteriorattack1418.png</filename>
	<path>C:\lees_project\fire-dataset-dunnings\images-224x224\train\fire\Firefighterhelmetcaminteriorattack1418.png</path>
	<source>
		<database>Unknown</database>
	</source>
	<size>
		<width>224</width>
		<height>224</height>
		<depth>3</depth>
	</size>
	<segmented>0</segmented>
	<object>
		<name>fire_l</name>
		<pose>Unspecified</pose>
		<truncated>0</truncated>
		<difficult>0</difficult>
		<bndbox>
			<xmin>50</xmin>
			<ymin>100</ymin>
			<xmax>55</xmax>
			<ymax>110</ymax>
		</bndbox>
	</object>
	<object>
		<name>fire_l</name>
		<pose>Unspecified</pose>
		<truncated>0</truncated>
		<difficult>0</difficult>
		<bndbox>
			<xmin>111</xmin>
			<ymin>72</ymin>
			<xmax>124</xmax>
			<ymax>93</ymax>
		</bndbox>
	</object>
	<object>
		<name>fire_h</name>
		<pose>Unspecified</pose>
		<truncated>0</truncated>
		<difficult>0</difficult>
		<bndbox>
			<xmin>122</xmin>
			<ymin>93</ymin>
			<xmax>140</xmax>
			<ymax>131</ymax>
		</bndbox>
	</object>
	<object>
		<name>fire_h</name>
		<pose>Unspecified</pose>
		<truncated>0</truncated>
		<difficult>0</difficult>
		<bndbox>
			<xmin>144</xmin>
			<ymin>109</ymin>
			<xmax>155</xmax>
			<ymax>157</ymax>
		</bndbox>
	</object>
</annotation>
